LICENSE
MANIFEST.in
README.md
setup.py
django_liveserver/__init__.py
django_liveserver/testcases.py
django_liveserver.egg-info/PKG-INFO
django_liveserver.egg-info/SOURCES.txt
django_liveserver.egg-info/dependency_links.txt
django_liveserver.egg-info/requires.txt
django_liveserver.egg-info/top_level.txt