Metadata-Version: 1.0
Name: django-liveserver
Version: 0.1a-1
Summary: A backport of the Django 1.4 LiveServerTestCase for 1.3
Home-page: UNKNOWN
Author: Alec Koumjian
Author-email: akoumjian@gmail.com
License: UNKNOWN
Keywords: django live server selenium test testcase
Platform: UNKNOWN
